engine/__init__.py
engine/config.py
engine/exceptions.py
engine/adapters/__init__.py
engine/adapters/cli.py
engine/domain/__init__.py
engine/domain/datamap.py
engine/domain/template.py
engine/reports/__init__.py
engine/reports/validation.py
engine/repository/__init__.py
engine/repository/datamap.py
engine/repository/master.py
engine/repository/templates.py
engine/serializers/__init__.py
engine/serializers/datamap.py
engine/serializers/template.py
engine/use_cases/__init__.py
engine/use_cases/output.py
engine/use_cases/parsing.py
engine/use_cases/typing.py
engine/utils/__init__.py
engine/utils/extraction.py
engine/utils/validation.py
tests/__init__.py
tests/conftest.py
tests/test_configuration.py
tests/test_datamap_parser.py
tests/test_hashing.py
tests/test_template_parser.py
tests/adapters/test_cli.py
tests/reports/test_csv_validation_report.py
tests/repository/test_in_memory_repos.py
tests/serializers/test_datamap_serializers.py
tests/serializers/test_template_data_serializers.py
tests/use_cases/test_datamap_use_cases.py
tests/use_cases/test_master_from_org_templates.py
tests/use_cases/test_populate_templates_from_master.py
tests/use_cases/test_template_parser_use_cases.py
tests/utils/test_error_reporting.py
tests/utils/test_utils.py
tests/utils/test_validation.py
bcompiler_engine-1.1.7.dist-info/LICENSE.txt
bcompiler_engine-1.1.7.dist-info/METADATA
bcompiler_engine-1.1.7.dist-info/WHEEL
bcompiler_engine-1.1.7.dist-info/top_level.txt
bcompiler_engine-1.1.7.dist-info/RECORD
