Metadata-Version: 2.1
Name: bcompiler-engine
Version: 1.1.7
Summary: Library for parsing spreadsheets using datamaps
Home-page: https://github.com/hammerheadlemon/bcompiler-engine
Author: Matthew Lemon
Author-email: Matthew Lemon <y@yulqen.org>
License: MIT
Classifier: Programming Language :: Python :: 3
Classifier: Environment :: Console
Classifier: License :: OSI Approved :: MIT License
Requires-Python: >=3.10
License-File: LICENSE.txt
Requires-Dist: openpyxl >=3.1.2
Requires-Dist: appdirs >=1.4.4
Requires-Dist: wheel >=0.41.2
